NLP_EXPERIMENTS/Experiment No 1.docx
NLP_EXPERIMENTS/Experiment No 3.docx
NLP_EXPERIMENTS/Experiment no. 2.pdf
NLP_EXPERIMENTS/Experiment no. 4.docx
NLP_EXPERIMENTS/Experiment no. 5.docx
NLP_EXPERIMENTS/Experiment no. 6.docx
NLP_EXPERIMENTS/Experiment no. 7.docx
NLP_EXPERIMENTS/Experiment no. 8.docx
NLP_EXPERIMENTS/__init__.py
NLP_EXPERIMENTS/main.py
NLP_EXPERIMENTS-1.6.dist-info/METADATA
NLP_EXPERIMENTS-1.6.dist-info/WHEEL
NLP_EXPERIMENTS-1.6.dist-info/top_level.txt
NLP_EXPERIMENTS-1.6.dist-info/RECORD
