Metadata-Version: 2.1
Name: NLP_EXPERIMENTS
Version: 1.6
Summary: NLP Expts
Author: a
Author-email: a@gmail.com
